MANIFEST.in
README.md
requirements.txt
setup.cfg
setup.py
efm8boot/__init__.py
efm8boot/bootloader.py
efm8boot/hid_bootloader.py
efm8boot/ids.py
efm8boot/records.py
efm8boot/smbus_bootloader.py
efm8boot/uart_bootloader.py
efm8boot.egg-info/PKG-INFO
efm8boot.egg-info/SOURCES.txt
efm8boot.egg-info/dependency_links.txt
efm8boot.egg-info/requires.txt
efm8boot.egg-info/top_level.txt
scripts/efm8boot-cli.py